bootloop/__init__.py
bootloop-0.0.1.dist-info/METADATA
bootloop-0.0.1.dist-info/WHEEL
bootloop-0.0.1.dist-info/top_level.txt
bootloop-0.0.1.dist-info/RECORD
