Metadata-Version: 2.4
Name: bootloop
Version: 0.0.1
Summary: BootLoop
Author: Noah Pacik-Nelson
Author-email: noah@bootloop.ai
Requires-Python: >=3.6
Dynamic: author
Dynamic: author-email
Dynamic: requires-python
Dynamic: summary
